dwat-0.7.7.dist-info/METADATA
dwat-0.7.7.dist-info/WHEEL
dwat-0.7.7.dist-info/licenses/LICENSE
dwat/__init__.py
dwat/dwat.cpython-310-powerpc64le-linux-gnu.so
dwat-0.7.7.dist-info/RECORD
