Metadata-Version: 2.4
Name: dwat
Version: 0.7.7
Classifier: License :: OSI Approved :: BSD License
Classifier: Programming Language :: Python
Classifier: Programming Language :: Rust
Classifier: Operating System :: POSIX
License-File: LICENSE
Summary: Library for accessing DWARF debug information
Home-Page: https://github.com/zolutal/dwat
Author: Jennifer Miller
Requires-Python: >=3.9
Project-URL: Repository, https://github.com/zolutal/dwat
Project-URL: Documentation, https://zolutal.github.io/dwat/
